source_zoho_crm/__init__.py
source_zoho_crm/api.py
source_zoho_crm/auth.py
source_zoho_crm/exceptions.py
source_zoho_crm/run.py
source_zoho_crm/source.py
source_zoho_crm/spec.json
source_zoho_crm/streams.py
source_zoho_crm/types.py
airbyte_source_zoho_crm-0.1.3.dist-info/METADATA
airbyte_source_zoho_crm-0.1.3.dist-info/WHEEL
airbyte_source_zoho_crm-0.1.3.dist-info/entry_points.txt
airbyte_source_zoho_crm-0.1.3.dist-info/RECORD
